CHANGES.txt
LICENSE
MANIFEST.in
README.md
README.txt
setup.py
bin/csv_to_gdx.py
bin/gdx_to_csv.py
gdxpds/__init__.py
gdxpds/_version.py
gdxpds/gdx.py
gdxpds/read_gdx.py
gdxpds/special.py
gdxpds/tools.py
gdxpds/write_gdx.py
gdxpds.egg-info/PKG-INFO
gdxpds.egg-info/SOURCES.txt
gdxpds.egg-info/dependency_links.txt
gdxpds.egg-info/requires.txt
gdxpds.egg-info/top_level.txt
gdxpds/test/CONVqn.gdx
gdxpds/test/OptimalCSPConfig_In.gdx
gdxpds/test/OptimalCSPConfig_Out.gdx
gdxpds/test/__init__.py
gdxpds/test/all_generator_properties_input.gdx
gdxpds/test/annual_generation.csv
gdxpds/test/conftest.py
gdxpds/test/installed_capacity.csv
gdxpds/test/test_conversions.py
gdxpds/test/test_read.py
gdxpds/test/test_session.py
gdxpds/test/test_specials.py
gdxpds/test/test_write.py