Metadata-Version: 2.1
Name: gdxpds
Version: 1.4.0
Summary: gdx-pandas is a python package to translate between gdx (GAMS data) and pandas
Home-page: https://github.com/NREL/gdx-pandas
Author: Elaine T. Hale
Author-email: elaine.hale@nrel.gov
Provides-Extra: test
Provides-Extra: admin
License-File: LICENSE
